MANIFEST.in
README.md
setup.cfg
setup.py
versioneer.py
csirtg_urlsml_tf/__init__.py
csirtg_urlsml_tf/_version.py
csirtg_urlsml_tf/constants.py
csirtg_urlsml_tf/train.py
csirtg_urlsml_tf.egg-info/PKG-INFO
csirtg_urlsml_tf.egg-info/SOURCES.txt
csirtg_urlsml_tf.egg-info/dependency_links.txt
csirtg_urlsml_tf.egg-info/entry_points.txt
csirtg_urlsml_tf.egg-info/requires.txt
csirtg_urlsml_tf.egg-info/top_level.txt
data/model.h5
data/weights.h5
data/word-dict.json
test/__init__.py
test/test_basics.py