Metadata-Version: 1.0
Name: csirtg-urlsml-tf
Version: 0.0a5
Summary: CSIRTG URLs ML Framework - TensorFlow
Home-page: https://github.com/csirtgadgets/csirtg-urlsml-tf-py
Author: Wes Young
Author-email: wes@csirtgadgets.com
License: MPLv2
Keywords: network,security
Platform: UNKNOWN
